Metadata-Version: 1.0
Name: Hatak_Statics
Version: 0.2.5
Summary: Statics plugin for Hatak.
Home-page: UNKNOWN
Author: UNKNOWN
Author-email: UNKNOWN
License: Apache License 2.0
Platform: UNKNOWN
